loopypy/__init__.py
loopypy/app.py
loopypy-1.0.6.dist-info/licenses/LICENSE
loopypy-1.0.6.dist-info/METADATA
loopypy-1.0.6.dist-info/WHEEL
loopypy-1.0.6.dist-info/top_level.txt
loopypy-1.0.6.dist-info/RECORD
