Metadata-Version: 2.4
Name: loopypy
Version: 1.0.6
Summary: An official Python wrapper for api.loopy5418.dev
Author-email: "loopy5418.dev" <admin@loopy5418.dev>
License-Expression: MIT
Project-URL: Homepage, https://github.com/api-loopy5418-dev/loopypy
Keywords: ai,wrapper,loopy,api
Classifier: Programming Language :: Python :: 3
Classifier: Operating System :: OS Independent
Requires-Python: >=3.7
License-File: LICENSE
Requires-Dist: requests
Dynamic: license-file
